[
    {
        "key": "sb",
        "value": "aCGzZ3x2RXrDhuZl03FE8Gn5",
        "domain": "facebook.com",
        "path": "/",
        "hostOnly": false,
        "creation": "2025-12-10T16:56:17.844Z",
        "lastAccessed": "2025-12-10T16:56:17.844Z"
    },
    {
        "key": "ps_l",
        "value": "1",
        "domain": "facebook.com",
        "path": "/",
        "hostOnly": false,
        "creation": "2025-12-10T16:56:17.844Z",
        "lastAccessed": "2025-12-10T16:56:17.844Z"
    },
    {
        "key": "ps_n",
        "value": "1",
        "domain": "facebook.com",
        "path": "/",
        "hostOnly": false,
        "creation": "2025-12-10T16:56:17.844Z",
        "lastAccessed": "2025-12-10T16:56:17.844Z"
    },
    {
        "key": "dpr",
        "value": "2.1988937854766846",
        "domain": "facebook.com",
        "path": "/",
        "hostOnly": false,
        "creation": "2025-12-10T16:56:17.844Z",
        "lastAccessed": "2025-12-10T16:56:17.844Z"
    },
    {
        "key": "datr",
        "value": "VXotacAM7W0stIRQ_VT0EWmd",
        "domain": "facebook.com",
        "path": "/",
        "hostOnly": false,
        "creation": "2025-12-10T16:56:17.844Z",
        "lastAccessed": "2025-12-10T16:56:17.844Z"
    },
    {
        "key": "c_user",
        "value": "61584694736902",
        "domain": "facebook.com",
        "path": "/",
        "hostOnly": false,
        "creation": "2025-12-10T16:56:17.844Z",
        "lastAccessed": "2025-12-10T16:56:17.844Z"
    },
    {
        "key": "fr",
        "value": "1VnFQi0uFei7sY6Nw.AWfaBiAVA5fF71Ovnpd-0eCE8xaZ9yjnmmB0qjhn_2pKhd7jdvo.BpOaUE..AAA.0.0.BpOaUE.AWcjo1nw1XvCRLlkz7EDILsESJU",
        "domain": "facebook.com",
        "path": "/",
        "hostOnly": false,
        "creation": "2025-12-10T16:56:17.844Z",
        "lastAccessed": "2025-12-10T16:56:17.844Z"
    },
    {
        "key": "xs",
        "value": "3%3AT25EE-154KxPbw%3A2%3A1765385463%3A-1%3A-1%3A%3AAcy9AGH21ntNyvtmuyek8uR8Wrez3Uc4-wuSIUVDqA",
        "domain": "facebook.com",
        "path": "/",
        "hostOnly": false,
        "creation": "2025-12-10T16:56:17.844Z",
        "lastAccessed": "2025-12-10T16:56:17.844Z"
    },
    {
        "key": "presence",
        "value": "C%7B%22lm3%22%3A%22g.23996385673317877%22%2C%22t3%22%3A%5B%7B%22o%22%3A0%2C%22i%22%3A%22g.9224233121019051%22%7D%5D%2C%22utc3%22%3A1765385503323%2C%22v%22%3A1%7D",
        "domain": "facebook.com",
        "path": "/",
        "hostOnly": false,
        "creation": "2025-12-10T16:56:17.844Z",
        "lastAccessed": "2025-12-10T16:56:17.844Z"
    },
    {
        "key": "wd",
        "value": "980x1759",
        "domain": "facebook.com",
        "path": "/",
        "hostOnly": false,
        "creation": "2025-12-10T16:56:17.844Z",
        "lastAccessed": "2025-12-10T16:56:17.844Z"
    }
]
